PyPlayer/__init__.py
py_media_player-1.0.1.dist-info/METADATA
py_media_player-1.0.1.dist-info/WHEEL
py_media_player-1.0.1.dist-info/top_level.txt
py_media_player-1.0.1.dist-info/RECORD
